zowie_agent_sdk/__init__.py
zowie_agent_sdk/agent.py
zowie_agent_sdk/auth.py
zowie_agent_sdk/context.py
zowie_agent_sdk/domain.py
zowie_agent_sdk/http.py
zowie_agent_sdk/llm/__init__.py
zowie_agent_sdk/llm/base.py
zowie_agent_sdk/llm/google.py
zowie_agent_sdk/llm/openai.py
zowie_agent_sdk/protocol.py
zowie_agent_sdk/py.typed
zowie_agent_sdk/utils.py
zowie_agent_sdk-0.5.0.dist-info/LICENSE
zowie_agent_sdk-0.5.0.dist-info/METADATA
zowie_agent_sdk-0.5.0.dist-info/WHEEL
zowie_agent_sdk-0.5.0.dist-info/entry_points.txt
zowie_agent_sdk-0.5.0.dist-info/RECORD
