Metadata-Version: 2.3
Name: zowie-agent-sdk
Version: 0.5.0
Summary: 
License: MIT
Author: zowie
Author-email: support@zowie.ai
Requires-Python: >=3.9
Classifier: License :: OSI Approved :: MIT License
Classifier: Programming Language :: Python :: 3
Classifier: Programming Language :: Python :: 3.9
Classifier: Programming Language :: Python :: 3.10
Classifier: Programming Language :: Python :: 3.11
Classifier: Programming Language :: Python :: 3.12
Classifier: Programming Language :: Python :: 3.13
Requires-Dist: fastapi (>=0.111.0,<0.112.0)
Requires-Dist: google-genai (>=1.31.0,<2.0.0)
Requires-Dist: openai (>=1.107.0,<2.0.0)
Requires-Dist: pydantic (>=2.7,<3.0)
Requires-Dist: requests (>=2.32.5,<3.0.0)
